easy_sge/__init__.py
easy_sge/experiences_manager.py
easy_sge/jinja2_templates/grid_template.j2
easy_sge/tests/simple_workflow.py
easy_sge/tests/test_e2e.py
easy_sge-1.0.2.dist-info/LICENSE
easy_sge-1.0.2.dist-info/WHEEL
easy_sge-1.0.2.dist-info/METADATA
easy_sge-1.0.2.dist-info/RECORD
