Metadata-Version: 2.1
Name: easy_sge
Version: 1.0.2
Summary: Module that manage SGE experiences, from parameters to grid executions
Author-email: William Droz <william.droz@idiap.ch>
Classifier: License :: OSI Approved :: MIT License
Requires-Dist: jinja2 >=2.10,<3.0
Requires-Dist: markupsafe ==2.0.1
Requires-Dist: black == 22.3.0 ; extra == "dev"
Requires-Dist: coverage >= 6.4.2,<7.0.0 ; extra == "dev"
Requires-Dist: flake8 >=3.8.3,<4.0.0 ; extra == "dev"
Requires-Dist: mypy >=0.971,<1.0 ; extra == "dev"
Requires-Dist: pre-commit >=2.17.0,<3.0.0 ; extra == "dev"
Requires-Dist: pytest >=7.1.2,<8.0.0 ; extra == "dev"
Project-URL: Home, https://gitlab.idiap.ch/devel/easy_sge
Provides-Extra: dev
